splice/__init__.py
splice/components.py
splice/connections.py
splice/enums.py
splice/export.py
splice/harness.py
splice/labels.py
splice/parts.py
splice/types.py
splice/utils.py
splice/validation.py
splice_py-0.2.0.dist-info/licenses/LICENSE
splice_py-0.2.0.dist-info/METADATA
splice_py-0.2.0.dist-info/WHEEL
splice_py-0.2.0.dist-info/top_level.txt
splice_py-0.2.0.dist-info/RECORD
