Metadata-Version: 2.4
Name: splice-py
Version: 0.2.0
Summary: Python library for programmatic Splice harness generation
Author-email: Splice CAD <info@splice-cad.com>
Maintainer-email: Splice CAD <info@splice-cad.com>
License: MIT
Project-URL: Homepage, https://github.com/splice-cad/splice-py
Project-URL: Documentation, https://github.com/splice-cad/splice-py#readme
Project-URL: Repository, https://github.com/splice-cad/splice-py.git
Project-URL: Issues, https://github.com/splice-cad/splice-py/issues
Keywords: cable,harness,wiring,manufacturing,splice
Classifier: Development Status :: 3 - Alpha
Classifier: Intended Audience :: Developers
Classifier: Intended Audience :: Manufacturing
Classifier: License :: OSI Approved :: MIT License
Classifier: Programming Language :: Python :: 3
Classifier: Programming Language :: Python :: 3.8
Classifier: Programming Language :: Python :: 3.9
Classifier: Programming Language :: Python :: 3.10
Classifier: Programming Language :: Python :: 3.11
Classifier: Programming Language :: Python :: 3.12
Classifier: Topic :: Software Development :: Libraries :: Python Modules
Classifier: Topic :: Scientific/Engineering
Requires-Python: >=3.8
License-File: LICENSE
Provides-Extra: dev
Requires-Dist: pytest>=7.0; extra == "dev"
Requires-Dist: pytest-cov>=4.0; extra == "dev"
Requires-Dist: mypy>=1.0; extra == "dev"
Requires-Dist: black>=23.0; extra == "dev"
Requires-Dist: flake8>=6.0; extra == "dev"
Requires-Dist: isort>=5.0; extra == "dev"
Provides-Extra: upload
Requires-Dist: requests>=2.25.0; extra == "upload"
Dynamic: license-file
